MANIFEST.in
setup.cfg
setup.py
pypolyagamma/__init__.py
pypolyagamma/pypolyagamma.cpp
pypolyagamma/pypolyagamma.pyx
pypolyagamma/cpp/InvertY.cpp
pypolyagamma/cpp/InvertY.hpp
pypolyagamma/cpp/PolyaGamma.cpp
pypolyagamma/cpp/PolyaGamma.h
pypolyagamma/cpp/PolyaGammaAlt.cpp
pypolyagamma/cpp/PolyaGammaAlt.h
pypolyagamma/cpp/PolyaGammaHybrid.h
pypolyagamma/cpp/PolyaGammaOMP.h
pypolyagamma/cpp/PolyaGammaPar.h
pypolyagamma/cpp/PolyaGammaSP.cpp
pypolyagamma/cpp/PolyaGammaSP.h
pypolyagamma/cpp/PolyaGammaSmallB.cpp
pypolyagamma/cpp/PolyaGammaSmallB.h
pypolyagamma/cpp/include/GRNG.cpp
pypolyagamma/cpp/include/GRNG.hpp
pypolyagamma/cpp/include/RNG.cpp
pypolyagamma/cpp/include/RNG.hpp
pypolyagamma/cpp/include/SRNG.hpp
pypolyagamma_3.egg-info/PKG-INFO
pypolyagamma_3.egg-info/SOURCES.txt
pypolyagamma_3.egg-info/dependency_links.txt
pypolyagamma_3.egg-info/requires.txt
pypolyagamma_3.egg-info/top_level.txt