Metadata-Version: 1.1
Name: pypolyagamma-3
Version: 0.1.8
Summary: Cython wrappers for Polya gamma random number generation based on Jesse
Home-page: http://www.github.com/Savvysherpa/pypolyagamma
Author: Matt Burbidge
Author-email: mburbidge@savvysherpa.com
License: MIT
Keywords: monte-carlo,polya,gamma
Platform: ALL
Classifier: Intended Audience :: Science/Research
Classifier: Programming Language :: Python :: 3.5
Classifier: Programming Language :: C++
